acpibacklight/__init__.py
acpibacklight/acpibacklight.py
acpibacklight/cli.py
acpibacklight-0.2.0.dist-info/DESCRIPTION.rst
acpibacklight-0.2.0.dist-info/METADATA
acpibacklight-0.2.0.dist-info/RECORD
acpibacklight-0.2.0.dist-info/WHEEL
acpibacklight-0.2.0.dist-info/entry_points.txt
acpibacklight-0.2.0.dist-info/metadata.json
acpibacklight-0.2.0.dist-info/top_level.txt
