Metadata-Version: 2.0
Name: acpibacklight
Version: 0.2.0
Summary: Library and script for changing brightness on Linux via acpi. Allows for easing animations too!
Home-page: UNKNOWN
Author: Aaron Abbott
Author-email: aabmass@gmail.com
License: UNKNOWN
Keywords: acpi brightness backlight easing animation
Platform: UNKNOWN
Requires-Dist: PyTweening (==1.0.3)
